bsc_utils/__init__.py
bsc_utils/chat.py
bsc_utils/config.py
bsc_utils/crawl.py
bsc_utils/database.py
bsc_utils/exceptions.py
bsc_utils/helpers.py
bsc_utils/parallel.py
bsc_utils/resources/queries.py
bsc_utils/resources/sessions.json
bsc_utils/time.py
bsc_utils/visual.py
bsc_utils-1.0.6.dist-info/METADATA
bsc_utils-1.0.6.dist-info/WHEEL
bsc_utils-1.0.6.dist-info/RECORD
