Metadata-Version: 2.1
Name: bsc-utils
Version: 1.0.6
Summary: Utils for BSC Quants
Home-page: https://github.com/dang-trung/bsc-utils
License: MIT
Author: Trung Dang
Author-email: dangtrung96@gmail.com
Maintainer: Trung Dang
Maintainer-email: dangtrung96@gmail.com
Requires-Python: >=3.11,<4.0
Classifier: Intended Audience :: Developers
Classifier: License :: OSI Approved :: MIT License
Classifier: Operating System :: OS Independent
Classifier: Programming Language :: Python :: 3
Classifier: Programming Language :: Python :: 3.11
Classifier: Topic :: Software Development :: Libraries :: Python Modules
Requires-Dist: dynaconf (>=3.2.3,<4.0.0)
Requires-Dist: numpy (>=1.25.2,<2.0.0)
Requires-Dist: oracledb (>=1.4.1,<2.0.0)
Requires-Dist: pandas (>=2.1.0,<3.0.0)
Requires-Dist: plotly (>=5.16.1,<6.0.0)
Requires-Dist: psycopg2 (>=2.9.7,<3.0.0)
Requires-Dist: pymssql (>=2.2.7,<3.0.0)
Requires-Dist: pyodbc (>=4.0.39,<5.0.0)
Requires-Dist: skpy (>=0.10.6,<0.11.0)
Requires-Dist: tqdm (>=4.66.1,<5.0.0)
Requires-Dist: yfinance (>=0.2.28,<0.3.0)
Project-URL: Repository, https://github.com/dang-trung/bsc-utils
